memoria/__init__.py
memoria/editor.py
memoria/game.py
memoria/highscore.py
memoria/list.py
memoria/memoria.py
memoria/settings.py
memoria/simpleaudio/LICENSE.txt
memoria/simpleaudio/README.rst
memoria/simpleaudio/__init__.py
memoria/simpleaudio/_simpleaudio.so
memoria/simpleaudio/simpleaudio.py
memoria_romaaeterna-1.0.0.data/data/share/applications/de.RomaAeterna.Memoria.desktop
memoria_romaaeterna-1.0.0.data/data/share/icons/hicolor/16x16/apps/de.RomaAeterna.Memoria.png
memoria_romaaeterna-1.0.0.data/data/share/icons/hicolor/22x22/apps/de.RomaAeterna.Memoria.png
memoria_romaaeterna-1.0.0.data/data/share/icons/hicolor/24x24/apps/de.RomaAeterna.Memoria.png
memoria_romaaeterna-1.0.0.data/data/share/icons/hicolor/256x256/apps/de.RomaAeterna.Memoria.png
memoria_romaaeterna-1.0.0.data/data/share/icons/hicolor/32x32/apps/de.RomaAeterna.Memoria.png
memoria_romaaeterna-1.0.0.data/data/share/icons/hicolor/48x48/apps/de.RomaAeterna.Memoria.png
memoria_romaaeterna-1.0.0.data/data/share/icons/hicolor/512x512/apps/de.RomaAeterna.Memoria.png
memoria_romaaeterna-1.0.0.data/data/share/locale/de/LC_MESSAGES/memoria.mo
memoria_romaaeterna-1.0.0.data/data/share/locale/en_GB/LC_MESSAGES/memoria.mo
memoria_romaaeterna-1.0.0.data/data/share/memoria/pixmaps/board.svg
memoria_romaaeterna-1.0.0.data/data/share/memoria/pixmaps/logo.png
memoria_romaaeterna-1.0.0.data/data/share/memoria/pixmaps/victory.png
memoria_romaaeterna-1.0.0.data/data/share/memoria/sounds/finish.wav
memoria_romaaeterna-1.0.0.data/data/share/memoria/sounds/found.wav
memoria_romaaeterna-1.0.0.data/data/share/memoria/sounds/start.wav
memoria_romaaeterna-1.0.0.data/data/share/memoria/ui/editor.ui
memoria_romaaeterna-1.0.0.data/data/share/memoria/ui/game.ui
memoria_romaaeterna-1.0.0.data/data/share/memoria/ui/highscore.ui
memoria_romaaeterna-1.0.0.data/data/share/memoria/ui/memoria.css
memoria_romaaeterna-1.0.0.data/data/share/memoria/ui/settings.ui
memoria_romaaeterna-1.0.0.dist-info/DESCRIPTION.rst
memoria_romaaeterna-1.0.0.dist-info/METADATA
memoria_romaaeterna-1.0.0.dist-info/RECORD
memoria_romaaeterna-1.0.0.dist-info/WHEEL
memoria_romaaeterna-1.0.0.dist-info/metadata.json
memoria_romaaeterna-1.0.0.dist-info/top_level.txt
